{
  "model": "nomic-ai/nomic-embed-text-v1.5",
  "embedding_dim": 768,
  "n_cases": 50,
  "targeted_accs": {
    "general_evaluative": 0.1,
    "harm_reduction": 0.5,
    "truthfulness": 0.2,
    "persona_honesty": 0.54,
    "anti_sycophancy": 0.56
  },
  "random_axis_stats": {
    "mean": 0.4916,
    "std": 0.12149666662094068,
    "min": 0.22,
    "max": 0.78
  },
  "random_accs": [
    0.52,
    0.62,
    0.3,
    0.66,
    0.46,
    0.34,
    0.4,
    0.6,
    0.46,
    0.4,
    0.36,
    0.66,
    0.62,
    0.6,
    0.54,
    0.56,
    0.56,
    0.56,
    0.24,
    0.46,
    0.52,
    0.54,
    0.6,
    0.38,
    0.5,
    0.42,
    0.5,
    0.78,
    0.68,
    0.48,
    0.6,
    0.52,
    0.54,
    0.46,
    0.56,
    0.44,
    0.32,
    0.48,
    0.52,
    0.46,
    0.54,
    0.68,
    0.3,
    0.6,
    0.3,
    0.64,
    0.52,
    0.46,
    0.38,
    0.4,
    0.28,
    0.34,
    0.24,
    0.46,
    0.54,
    0.48,
    0.64,
    0.38,
    0.28,
    0.48,
    0.4,
    0.44,
    0.6,
    0.42,
    0.74,
    0.36,
    0.62,
    0.58,
    0.48,
    0.36,
    0.66,
    0.42,
    0.46,
    0.5,
    0.58,
    0.4,
    0.54,
    0.76,
    0.48,
    0.38,
    0.38,
    0.34,
    0.36,
    0.66,
    0.36,
    0.4,
    0.5,
    0.62,
    0.44,
    0.4,
    0.32,
    0.56,
    0.66,
    0.76,
    0.56,
    0.58,
    0.56,
    0.58,
    0.6,
    0.7,
    0.48,
    0.5,
    0.46,
    0.52,
    0.6,
    0.44,
    0.48,
    0.62,
    0.5,
    0.5,
    0.64,
    0.38,
    0.48,
    0.4,
    0.56,
    0.56,
    0.54,
    0.22,
    0.44,
    0.42,
    0.66,
    0.52,
    0.36,
    0.6,
    0.54,
    0.44,
    0.62,
    0.5,
    0.74,
    0.72,
    0.6,
    0.42,
    0.5,
    0.28,
    0.56,
    0.46,
    0.56,
    0.3,
    0.24,
    0.56,
    0.58,
    0.28,
    0.52,
    0.26,
    0.58,
    0.4,
    0.46,
    0.3,
    0.62,
    0.5,
    0.56,
    0.56,
    0.66,
    0.4,
    0.34,
    0.44,
    0.54,
    0.46,
    0.64,
    0.64,
    0.4,
    0.24,
    0.5,
    0.64,
    0.58,
    0.3,
    0.32,
    0.58,
    0.5,
    0.34,
    0.48,
    0.28,
    0.44,
    0.7,
    0.44,
    0.52,
    0.26,
    0.52,
    0.72,
    0.52,
    0.44,
    0.56,
    0.52,
    0.6,
    0.54,
    0.46,
    0.4,
    0.48,
    0.62,
    0.26,
    0.56,
    0.4,
    0.26,
    0.56,
    0.52,
    0.52,
    0.6,
    0.38,
    0.48,
    0.54
  ],
  "perturbation": {
    "general_evaluative": {
      "original_accuracy": 0.1,
      "rephrased_accuracy": 0.16,
      "delta": 0.06,
      "cosine_similarity": 0.6551929712295532
    },
    "harm_reduction": {
      "original_accuracy": 0.5,
      "rephrased_accuracy": 0.8,
      "delta": 0.30000000000000004,
      "cosine_similarity": 0.3640744686126709
    },
    "truthfulness": {
      "original_accuracy": 0.2,
      "rephrased_accuracy": 0.18,
      "delta": -0.020000000000000018,
      "cosine_similarity": 0.2512194514274597
    },
    "persona_honesty": {
      "original_accuracy": 0.54,
      "rephrased_accuracy": 0.5,
      "delta": -0.040000000000000036,
      "cosine_similarity": 0.34521418809890747
    },
    "anti_sycophancy": {
      "original_accuracy": 0.56,
      "rephrased_accuracy": 0.46,
      "delta": -0.10000000000000003,
      "cosine_similarity": 0.14028993248939514
    }
  },
  "mean_perturbation_cosine": 0.35119820237159727,
  "transfer": {
    "on_diagonal_mean": 0.2844336219336219,
    "off_diagonal_mean": 0.3914930555555556
  },
  "pca": {
    "pc1_explained": 0.3372087776660919,
    "pc1_accuracy": 0.84
  }
}
