{
  "model": "BAAI/bge-small-en-v1.5",
  "n_cases": 50,
  "n_random_axes": 200,
  "seed": 42,
  "embedding_dim": 384,
  "targeted_accs": {
    "general_evaluative": 0.12,
    "harm_reduction": 0.56,
    "truthfulness": 0.24,
    "persona_honesty": 0.42,
    "anti_sycophancy": 0.62
  },
  "random_axis_stats": {
    "mean": 0.491,
    "std": 0.1000949549178179,
    "min": 0.22,
    "max": 0.76,
    "median": 0.5
  },
  "random_accs": [
    0.52,
    0.62,
    0.62,
    0.52,
    0.46,
    0.48,
    0.46,
    0.36,
    0.48,
    0.54,
    0.52,
    0.6,
    0.5,
    0.52,
    0.44,
    0.58,
    0.52,
    0.44,
    0.26,
    0.58,
    0.54,
    0.52,
    0.46,
    0.42,
    0.52,
    0.46,
    0.58,
    0.54,
    0.56,
    0.44,
    0.48,
    0.4,
    0.52,
    0.72,
    0.44,
    0.58,
    0.54,
    0.32,
    0.42,
    0.42,
    0.58,
    0.32,
    0.46,
    0.48,
    0.42,
    0.42,
    0.3,
    0.68,
    0.54,
    0.46,
    0.44,
    0.64,
    0.5,
    0.64,
    0.32,
    0.4,
    0.46,
    0.5,
    0.48,
    0.52,
    0.52,
    0.5,
    0.22,
    0.3,
    0.56,
    0.56,
    0.4,
    0.24,
    0.74,
    0.48,
    0.44,
    0.44,
    0.64,
    0.4,
    0.46,
    0.66,
    0.54,
    0.58,
    0.42,
    0.5,
    0.66,
    0.46,
    0.5,
    0.52,
    0.6,
    0.54,
    0.58,
    0.46,
    0.38,
    0.52,
    0.42,
    0.58,
    0.32,
    0.4,
    0.5,
    0.48,
    0.34,
    0.36,
    0.5,
    0.42,
    0.54,
    0.28,
    0.72,
    0.66,
    0.42,
    0.54,
    0.54,
    0.58,
    0.64,
    0.24,
    0.32,
    0.42,
    0.68,
    0.44,
    0.52,
    0.6,
    0.38,
    0.46,
    0.44,
    0.56,
    0.58,
    0.56,
    0.56,
    0.46,
    0.4,
    0.66,
    0.38,
    0.54,
    0.64,
    0.44,
    0.46,
    0.46,
    0.5,
    0.4,
    0.34,
    0.46,
    0.54,
    0.48,
    0.48,
    0.4,
    0.66,
    0.42,
    0.44,
    0.44,
    0.34,
    0.52,
    0.58,
    0.56,
    0.5,
    0.6,
    0.56,
    0.4,
    0.34,
    0.56,
    0.44,
    0.66,
    0.54,
    0.34,
    0.64,
    0.52,
    0.56,
    0.58,
    0.52,
    0.42,
    0.5,
    0.56,
    0.46,
    0.76,
    0.5,
    0.36,
    0.52,
    0.42,
    0.5,
    0.4,
    0.54,
    0.52,
    0.48,
    0.6,
    0.68,
    0.54,
    0.52,
    0.48,
    0.38,
    0.48,
    0.42,
    0.46,
    0.4,
    0.62,
    0.54,
    0.38,
    0.56,
    0.62,
    0.42,
    0.48,
    0.48,
    0.34,
    0.34,
    0.58,
    0.44,
    0.46
  ]
}
